icl/__init__.py
icl/inf.py
icl/itv.py
icl/itvset_rbtree.py
icl/itvset_treap.py
icl-0.0.0.dist-info/LICENSE
icl-0.0.0.dist-info/METADATA
icl-0.0.0.dist-info/WHEEL
icl-0.0.0.dist-info/top_level.txt
icl-0.0.0.dist-info/RECORD
