Metadata-Version: 2.1
Name: icl
Version: 0.0.0
Summary: Interval Container Library
Home-page: https://github.com/happyxianyu/icl
Author: happyxianyu
Author-email: happyxianyu623@outlook.com
License: Apache License 2.0
Platform: UNKNOWN
Requires-Python: >=3.8
Requires-Dist: infinity (>=1.5)
